feedforbot/__init__.py
feedforbot/__main__.py
feedforbot/cli.py
feedforbot/config.py
feedforbot/constants.py
feedforbot/core/__init__.py
feedforbot/core/article.py
feedforbot/core/cache.py
feedforbot/core/listeners.py
feedforbot/core/scheduler.py
feedforbot/core/transports.py
feedforbot/core/types.py
feedforbot/core/utils.py
feedforbot/exceptions.py
feedforbot/logger.py
feedforbot/utils.py
feedforbot/version.py
feedforbot-3.3.5.dist-info/entry_points.txt
feedforbot-3.3.5.dist-info/LICENSE
feedforbot-3.3.5.dist-info/WHEEL
feedforbot-3.3.5.dist-info/METADATA
feedforbot-3.3.5.dist-info/RECORD
