Metadata-Version: 2.1
Name: feedforbot
Version: 3.3.5
Summary: Forward links from RSS/Atom feeds to messengers
Home-page: https://github.com/shpaker/feedforbot
Author: Aleksandr Shpak
Author-email: shpaker@gmail.com
Requires-Python: >=3.10
Classifier: Programming Language :: Python :: 3
Classifier: Programming Language :: Python :: 3.10
Classifier: Programming Language :: Python :: 3.11
Requires-Dist: aiocron (>=1.8,<2.0)
Requires-Dist: aiofiles (>=23.2)
Requires-Dist: beautifulsoup4 (>=4.12,<5.0)
Requires-Dist: click (>=8.1,<9.0)
Requires-Dist: feedparser (>=6.0,<7.0)
Requires-Dist: httpx (>=0.26)
Requires-Dist: jinja2 (>=3.1,<4.0)
Requires-Dist: orjson (>=3.9,<4.0)
Requires-Dist: pydantic (>=2.0,<3.0)
Requires-Dist: pyyaml (>=6.0,<7.0)
Requires-Dist: sentry-sdk (>=2.0,<3.0)
Project-URL: Repository, https://github.com/shpaker/feedforbot
